Metadata-Version: 1.1
Name: squadron
Version: 0.6.3
Summary: Easy-to-use configuration and release management tool
Home-page: http://www.gosquadron.com
Author: Squadron
Author-email: info@gosquadron.com
License: MIT
Keywords: configuration management release deployment tool
Platform: UNKNOWN
Classifier: Development Status :: 3 - Alpha
Classifier: Intended Audience :: Developers
Classifier: Intended Audience :: System Administrators
Classifier: License :: OSI Approved :: MIT License
Classifier: Operating System :: POSIX
Classifier: Topic :: Software Development :: Testing
Classifier: Topic :: Utilities
